mysqlchain/__init__.py
mysqlchain/mysqlchain.py
mysqlchain/utils.py
mysqlchain-1.3.dist-info/LICENSE.txt
mysqlchain-1.3.dist-info/METADATA
mysqlchain-1.3.dist-info/WHEEL
mysqlchain-1.3.dist-info/top_level.txt
mysqlchain-1.3.dist-info/RECORD
