Metadata-Version: 2.1
Name: mysqlchain
Version: 1.3
Summary: chain operation mysql database
Home-page: https://www.kancloud.cn/lingfengcms/mysqlchain/2646275
Author: LingFeng
Author-email: 418155641@qq.com
Classifier: Programming Language :: Python :: 3
Classifier: License :: OSI Approved :: MIT License
Classifier: Operating System :: OS Independent
License-File: LICENSE.txt
Requires-Dist: PyMySQL>=1.0.2
